uitil/__init__.py
uitil/core.py
uitil-0.1.5.dist-info/METADATA
uitil-0.1.5.dist-info/WHEEL
uitil-0.1.5.dist-info/top_level.txt
uitil-0.1.5.dist-info/RECORD
